LICENSE
MANIFEST.in
README.rst
setup.py
agilego/__init__.py
agilego/api.bat
agilego/api.py
agilego/export.py
agilego/import.py
agilego/transform.py
agilego.egg-info/PKG-INFO
agilego.egg-info/SOURCES.txt
agilego.egg-info/dependency_links.txt
agilego.egg-info/requires.txt
agilego.egg-info/top_level.txt
agilego/cfg/db.json
agilego/cfg/env.json
agilego/cfg/na3x.json
agilego/cfg/data/jira-data-cleanup.json
agilego/cfg/data/jira-data-generation.json
agilego/cfg/data/cleanup/jira-data-cleanup.json
agilego/cfg/data/cleanup/jira-data-delete-board.json
agilego/cfg/data/cleanup/jira-data-delete-project.json
agilego/cfg/data/cleanup/jira-data-delete-sprint.json
agilego/cfg/data/cleanup/jira-data-delete-user.json
agilego/cfg/data/generation/jira-data-board-import.json
agilego/cfg/data/generation/jira-data-board-transform.json
agilego/cfg/data/generation/jira-data-create-issue.json
agilego/cfg/data/generation/jira-data-create-project.json
agilego/cfg/data/generation/jira-data-create-sprint.json
agilego/cfg/data/generation/jira-data-create-user.json
agilego/cfg/data/generation/jira-data-get-board.json
agilego/cfg/data/generation/jira-data-issues-export.json
agilego/cfg/data/generation/jira-data-set-issue-sprint.json
agilego/cfg/data/generation/jira-data-sprint-export.json
agilego/cfg/data/generation/jira-data-sprint-transform.json
agilego/cfg/data/generation/jira-data-static-entities-export.json
agilego/cfg/dependency/triggers.json
agilego/cfg/jira/jira-actual-status-request.json
agilego/cfg/jira/jira-components-request.json
agilego/cfg/jira/jira-export.json
agilego/cfg/jira/jira-import-actual.json
agilego/cfg/jira/jira-import-scope.json
agilego/cfg/jira/jira-server-date-request.json
agilego/cfg/jira/jira-set-issue-field.json
agilego/cfg/jira/jira-sprint-backlog-request.json
agilego/cfg/jira/jira-sprint-definition-request.json
agilego/cfg/jira/jira-team-request.json
agilego/cfg/log/api-logging-config.json
agilego/cfg/log/export-logging-config.json
agilego/cfg/log/graph-logging-config.json
agilego/cfg/log/import-logging-config.json
agilego/cfg/log/test-logging-config.json
agilego/cfg/log/transform-logging-config.json
