Metadata-Version: 1.2
Name: agilego
Version: 0.2.0
Summary: Sprint planner
Home-page: https://github.com/yero13/agilego.be
Author: Roman Yepifanov
Author-email: UNKNOWN
License: GNU GPL v2.0
Platform: UNKNOWN
Classifier: Development Status :: 3 - Alpha
Classifier: Environment :: Console
Classifier: Programming Language :: Python :: 3.6
Requires-Python: ~=3.6
